pushover_open_client/__init__.py
pushover_open_client/pushover_open_client.py
py_pushover_open_client-1.3.0.dist-info/LICENSE
py_pushover_open_client-1.3.0.dist-info/METADATA
py_pushover_open_client-1.3.0.dist-info/WHEEL
py_pushover_open_client-1.3.0.dist-info/top_level.txt
py_pushover_open_client-1.3.0.dist-info/RECORD
