Metadata-Version: 2.1
Name: py-pushover-open-client
Version: 1.3.0
Summary: Unofficial Python Bindings for PushOver Open Client API
Home-page: https://github.com/jonogreenz/py-pushover-open-client
Author: Jonathon Green
Author-email: aeirsoul@gmail.com
License: MIT
Keywords: pushover
Platform: UNKNOWN
Classifier: Development Status :: 5 - Production/Stable
Classifier: Intended Audience :: Developers
Classifier: Topic :: Software Development :: Build Tools
Classifier: License :: OSI Approved :: MIT License
Classifier: Programming Language :: Python :: 3.0
Classifier: Programming Language :: Python :: 3.1
Classifier: Programming Language :: Python :: 3.2
Classifier: Programming Language :: Python :: 3.3
Classifier: Programming Language :: Python :: 3.4
Classifier: Programming Language :: Python :: 3.5
Classifier: Programming Language :: Python :: 3.6
Classifier: Programming Language :: Python :: 3 :: Only
Requires-Dist: requests (>=2.14.0)
Requires-Dist: websocket-client (>=0.48.0)
